event_post_package/__init__.py
event_post_package/forms.py
event_post_package/models.py
event_post_package/urls.py
event_post_package/views.py
event_post_package/migrations/0001_initial.py
event_post_package/migrations/__init__.py
event_post_package/static/style.css
event_post_package/static/js/social.js
event_post_package/templates/user/post_delete.html
event_post_package/templates/user/post_detail.html
event_post_package/templates/user/post_edit.html
event_post_package/templates/user/post_wall.html
event_post_package/templates/user/profile.html
event_post_package/templates/user/profile_edit.html
event_post_package/templates/user/search-user.html
event_post_package-0.5.dist-info/METADATA
event_post_package-0.5.dist-info/WHEEL
event_post_package-0.5.dist-info/top_level.txt
event_post_package-0.5.dist-info/RECORD
