Metadata-Version: 2.1
Name: event-post-package
Version: 0.5
Summary: UNKNOWN
Home-page: UNKNOWN
License: UNKNOWN
Platform: UNKNOWN
Requires-Dist: Django
